[
  {
    "Id": "428854",
    "ThreadId": "208716",
    "Html": "<p>Hi,</p>\r\n<p>Copy and paste functionality works as expected in IE.</p>\r\n<p>In Firefox, the cut, copy, paste icons don't copy or paste text selected from the jHtmlArea. Does anyone know of a fix or a workaround?</p>\r\n<p>Thanks</p>\r\n<p>--</p>\r\n<p><span style=\"font-family:arial;font-size:small\">Abhi Muthiyan<br>Co-founder, CTO<br>Patagonia Health<br>919-649-6465<br>http://www.patagoniahealth.com<br>http://twitter.com/patagoniahealth</span></p>\r\n<p>&nbsp;</p>",
    "PostedDate": "2010-04-08T08:30:31.683-07:00",
    "UserRole": null,
    "MarkedAsAnswerDate": null
  }
]